gnwrapper/__init__.py
gnwrapper/brax.py
gym_notebook_wrapper-1.3.3.dist-info/LICENSE
gym_notebook_wrapper-1.3.3.dist-info/METADATA
gym_notebook_wrapper-1.3.3.dist-info/WHEEL
gym_notebook_wrapper-1.3.3.dist-info/top_level.txt
gym_notebook_wrapper-1.3.3.dist-info/RECORD
