Metadata-Version: 2.1
Name: gym-notebook-wrapper
Version: 1.3.3
Summary: Wrapper for running/rendering OpenAI Gym on Jupyter Notebook
Home-page: https://github.com/ymd-h/gym-notebook-wrapper
Author: Yamada Hiroyuki
Classifier: Development Status :: 4 - Beta
Classifier: Framework :: Jupyter
Classifier: Intended Audience :: Science/Research
Classifier: License :: OSI Approved :: MIT License
Classifier: Operating System :: POSIX :: Linux
Classifier: Programming Language :: Python :: 3 :: Only
Classifier: Topic :: Scientific/Engineering :: Artificial Intelligence
Classifier: Topic :: Software Development :: Libraries
License-File: LICENSE
Requires-Dist: gym
Requires-Dist: matplotlib
Requires-Dist: pyvirtualdisplay
Requires-Dist: ipython
Requires-Dist: moviepy
Provides-Extra: test
Requires-Dist: brax ; extra == 'test'
